telegrambot
tests
