Metadata-Version: 1.1
Name: telegrambot
Version: 2.4.0.dev10
Summary: Pluggable Python Telegram Bot
Home-page: https://www.github.com/wrboyce/telegrambot
Author: Will Boyce
Author-email: me@willboyce.com
License: License :: OSI Approved :: Apache Software License
Platform: Operating System :: MacOS :: MacOS X
Platform: Operating System :: POSIX
Classifier: Development Status :: 5 - Production/Stable
Classifier: Environment :: Console
Classifier: License :: OSI Approved :: Apache Software License
Classifier: Operating System :: MacOS :: MacOS X
Classifier: Operating System :: POSIX
Classifier: Programming Language :: Python :: 2.7
